tigrbl/README.md
tigrbl/__init__.py
tigrbl/api/__init__.py
tigrbl/api/_api.py
tigrbl/api/api_spec.py
tigrbl/api/mro_collect.py
tigrbl/api/shortcuts.py
tigrbl/api/tigrbl_api.py
tigrbl/app/__init__.py
tigrbl/app/_app.py
tigrbl/app/_model_registry.py
tigrbl/app/app_spec.py
tigrbl/app/mro_collect.py
tigrbl/app/shortcuts.py
tigrbl/app/tigrbl_app.py
tigrbl/bindings/__init__.py
tigrbl/bindings/api/__init__.py
tigrbl/bindings/api/common.py
tigrbl/bindings/api/include.py
tigrbl/bindings/api/resource_proxy.py
tigrbl/bindings/api/rpc.py
tigrbl/bindings/columns.py
tigrbl/bindings/handlers/__init__.py
tigrbl/bindings/handlers/builder.py
tigrbl/bindings/handlers/ctx.py
tigrbl/bindings/handlers/identifiers.py
tigrbl/bindings/handlers/namespaces.py
tigrbl/bindings/handlers/steps.py
tigrbl/bindings/hooks.py
tigrbl/bindings/model.py
tigrbl/bindings/model_helpers.py
tigrbl/bindings/model_registry.py
tigrbl/bindings/rest/__init__.py
tigrbl/bindings/rest/attach.py
tigrbl/bindings/rest/collection.py
tigrbl/bindings/rest/common.py
tigrbl/bindings/rest/fastapi.py
tigrbl/bindings/rest/helpers.py
tigrbl/bindings/rest/io.py
tigrbl/bindings/rest/io_headers.py
tigrbl/bindings/rest/member.py
tigrbl/bindings/rest/router.py
tigrbl/bindings/rest/routing.py
tigrbl/bindings/rpc.py
tigrbl/bindings/schemas/__init__.py
tigrbl/bindings/schemas/builder.py
tigrbl/bindings/schemas/defaults.py
tigrbl/bindings/schemas/utils.py
tigrbl/column/README.md
tigrbl/column/__init__.py
tigrbl/column/_column.py
tigrbl/column/column_spec.py
tigrbl/column/field_spec.py
tigrbl/column/infer/__init__.py
tigrbl/column/infer/core.py
tigrbl/column/infer/jsonhints.py
tigrbl/column/infer/planning.py
tigrbl/column/infer/types.py
tigrbl/column/infer/utils.py
tigrbl/column/io_spec.py
tigrbl/column/mro_collect.py
tigrbl/column/shortcuts.py
tigrbl/column/storage_spec.py
tigrbl/config/__init__.py
tigrbl/config/constants.py
tigrbl/config/defaults.py
tigrbl/config/resolver.py
tigrbl/core/__init__.py
tigrbl/core/crud/__init__.py
tigrbl-0.3.3.dist-info/METADATA
tigrbl-0.3.3.dist-info/WHEEL
tigrbl-0.3.3.dist-info/licenses/LICENSE
tigrbl-0.3.3.dist-info/RECORD
