Metadata-Version: 2.4
Name: tigrbl
Version: 0.3.3
Summary: Automatic API generation tools by Swarmauri.
License-Expression: Apache-2.0
License-File: LICENSE
Keywords: tigrbl,sdk,standards
Author: Swarmauri Team
Author-email: team@swarmauri.com
Requires-Python: >=3.10,<3.13
Classifier: License :: OSI Approved :: Apache Software License
Classifier: Development Status :: 3 - Alpha
Classifier: Programming Language :: Python :: 3.10
Classifier: Programming Language :: Python :: 3.11
Classifier: Programming Language :: Python :: 3.12
Classifier: Programming Language :: Python
Classifier: Programming Language :: Python :: 3
Classifier: Programming Language :: Python :: 3 :: Only
Provides-Extra: postgres
Provides-Extra: templates
Provides-Extra: tests
Requires-Dist: aiosqlite (>=0.19.0)
Requires-Dist: asyncpg (>=0.30.0) ; extra == "postgres"
Requires-Dist: fastapi (>=0.100.0)
Requires-Dist: greenlet (>=3.2.3)
Requires-Dist: httpx (>=0.27.0)
Requires-Dist: jinja2 (>=3.1.4) ; extra == "templates"
Requires-Dist: psycopg2-binary (>=2.9.9) ; extra == "postgres"
Requires-Dist: pydantic (>=2.0.0)
Requires-Dist: sqlalchemy (>=2.0)
Requires-Dist: swarmauri_base
Requires-Dist: swarmauri_core
Requires-Dist: swarmauri_standard
Requires-Dist: tigrbl-tests ; extra == "tests"
Requires-Dist: uvicorn
